odoo/addons/website_mass_mailing_name/README.rst
odoo/addons/website_mass_mailing_name/__init__.py
odoo/addons/website_mass_mailing_name/__manifest__.py
odoo/addons/website_mass_mailing_name/controllers/__init__.py
odoo/addons/website_mass_mailing_name/controllers/main.py
odoo/addons/website_mass_mailing_name/demo/assets.xml
odoo/addons/website_mass_mailing_name/i18n/de.po
odoo/addons/website_mass_mailing_name/i18n/es.po
odoo/addons/website_mass_mailing_name/i18n/fr.po
odoo/addons/website_mass_mailing_name/i18n/hr.po
odoo/addons/website_mass_mailing_name/i18n/pt.po
odoo/addons/website_mass_mailing_name/i18n/sl.po
odoo/addons/website_mass_mailing_name/i18n/website_mass_mailing_name.pot
odoo/addons/website_mass_mailing_name/readme/CONTRIBUTORS.rst
odoo/addons/website_mass_mailing_name/readme/DESCRIPTION.rst
odoo/addons/website_mass_mailing_name/readme/USAGE.rst
odoo/addons/website_mass_mailing_name/static/description/icon.png
odoo/addons/website_mass_mailing_name/static/description/index.html
odoo/addons/website_mass_mailing_name/static/src/css/website_mass_mailing_name.scss
odoo/addons/website_mass_mailing_name/static/src/js/editor_and_public_tour.js
odoo/addons/website_mass_mailing_name/static/src/js/website_mass_mailing_name.js
odoo/addons/website_mass_mailing_name/templates/assets.xml
odoo/addons/website_mass_mailing_name/templates/snippets.xml
odoo/addons/website_mass_mailing_name/tests/__init__.py
odoo/addons/website_mass_mailing_name/tests/test_ui.py
odoo12_addon_website_mass_mailing_name-12.0.1.0.0.99.dev7.dist-info/METADATA
odoo12_addon_website_mass_mailing_name-12.0.1.0.0.99.dev7.dist-info/WHEEL
odoo12_addon_website_mass_mailing_name-12.0.1.0.0.99.dev7.dist-info/top_level.txt
odoo12_addon_website_mass_mailing_name-12.0.1.0.0.99.dev7.dist-info/RECORD
